{
    "basic_info": {
      "name": "Nouh RIFAI",
      "titles": [ "Data Scientist", "Data Engineer", "Machine Learning Engineer", "Fullstack Web Developer", "Mobile App Developer" ],
      "social": [
        {
          "name": "github",
          "url": "https://github.com/nouhRifai",
          "class": "fab fa-github"
        },
        {
          "name": "linkedIn",
          "url": "https://www.linkedin.com/in/nouh-rifai/",
          "class": "fab fa-linkedin"
        }
      ],
      "image": "my_profile.JPG"
    },
    "skills": {
      "labels": ["Machine Learning", "Deep Learning", "AI", "Data Engineering", "Data Analysis", "Data Visualization", "Business Intelligence", "Web Development", "Mobile Development", "DevOps", "MLOps"],
      "datasets": [
        {
          "label": "My General Interest",
          "data": [9, 8.5, 8, 8.5, 8, 8.5, 7.5, 7, 7, 6, 7],
          "backgroundColor": "rgba(255, 99, 132, 0.2)",
          "borderColor": "rgba(255, 99, 132, 1)",
          "borderWidth": 1
        }
      ]
    },
    "skills_tech": {
      "labels": ["SQL", "Python", "R", "Flask", "Django", "NodeJs", "Express", "J2EE", "Springboot", "VB", "C#", "React", "React Native","RESTful Api"],
      "datasets": [
        {
          "label": "My Technological Interest",
          "data": [8.5, 9, 8.5, 8.3, 7.7, 7, 7, 7, 7.5, 4, 6, 5.5, 5,8],
          "backgroundColor": "rgba(255, 99, 132, 0.2)",
          "borderColor": "rgba(255, 99, 132, 1)",
          "borderWidth": 1
        },
        {
          "label": "My Technological Skills",
          "data": [8.5, 9, 8, 8, 7.5, 7.7, 7, 8, 7.5, 6, 7, 7.5, 6.7,8],
          "backgroundColor": "rgba(137, 196, 244, 0.2)",
          "borderColor": "rgba(1, 1, 122, 1)",
          "borderWidth": 1
        }
      ]
    },
    "skills_data": {
      "labels": ["Supervised L.", "Unsupervised L.", "Semi-Supervised L.", "Reinforcement L.", "Neural Networks", "NLP", "Data Cleansing", "Data Dim. Reduction", "DataViz", "SGBD"],
      "datasets": [
        {
          "label": "My Interest in Data Science",
          "data": [9, 8, 6, 7, 7, 7, 7.5, 7.5, 8, 8],
          "backgroundColor": "rgba(255, 99, 132, 0.2)",
          "borderColor": "rgba(255, 99, 132, 1)",
          "borderWidth": 1
        }
      ]
    }
  }